pypayment/__init__.py
pypayment/enums/__init__.py
pypayment/enums/commission.py
pypayment/enums/status.py
pypayment/exceptions.py
pypayment/payment.py
pypayment/providers/__init__.py
pypayment/providers/aaio.py
pypayment/providers/betatransfer.py
pypayment/providers/lava.py
pypayment/providers/payok.py
pypayment/providers/qiwi.py
pypayment/providers/yoomoney.py
pypayment-1.8.1.dist-info/METADATA
pypayment-1.8.1.dist-info/WHEEL
pypayment-1.8.1.dist-info/licenses/LICENSE
pypayment-1.8.1.dist-info/RECORD
