Metadata-Version: 2.4
Name: pypayment
Version: 1.8.1
Summary: Payment Providers API Wrapper
License: Apache-2.0
License-File: LICENSE
Keywords: payment,api,wrapper,payment-gateway,payment-provider
Author: Tim
Author-email: herew26@gmail.com
Requires-Python: >=3.8,<4.0
Classifier: Development Status :: 5 - Production/Stable
Classifier: Intended Audience :: Developers
Classifier: License :: OSI Approved :: Apache Software License
Classifier: Operating System :: OS Independent
Classifier: Programming Language :: Python :: 3
Classifier: Programming Language :: Python :: 3.8
Classifier: Programming Language :: Python :: 3.9
Classifier: Programming Language :: Python :: 3.10
Classifier: Programming Language :: Python :: 3.11
Classifier: Programming Language :: Python :: 3.12
Classifier: Programming Language :: Python :: 3.13
Classifier: Programming Language :: Python :: 3.14
Classifier: Typing :: Typed
Requires-Dist: requests (>=2.32.3,<3.0.0)
Project-URL: Documentation, https://timnekk.github.io/PyPayment/
Project-URL: Homepage, https://github.com/TimNekk/pypayment
Project-URL: Repository, https://github.com/TimNekk/pypayment.git
